{
  "instrument": "piano",
  "chords": {
    "A": [
      {
        "notes": [
          "A",
          "C#",
          "E"
        ]
      }
    ],
    "A#": [
      {
        "notes": [
          "Bb",
          "D",
          "F"
        ]
      }
    ],
    "A#4": [
      {
        "notes": [
          "Bb",
          "Eb",
          "G#",
          "C#"
        ]
      }
    ],
    "A#7": [
      {
        "notes": [
          "Bb",
          "D",
          "F",
          "G#"
        ]
      }
    ],
    "A#7M": [
      {
        "notes": [
          "Bb",
          "D",
          "F",
          "A"
        ]
      }
    ],
    "A#dim": [
      {
        "notes": [
          "Bb",
          "C#",
          "E"
        ]
      }
    ],
    "A#dim7": [
      {
        "notes": [
          "Bb",
          "C#",
          "E",
          "G"
        ]
      }
    ],
    "A#m": [
      {
        "notes": [
          "Bb",
          "C#",
          "F"
        ]
      }
    ],
    "A#m7": [
      {
        "notes": [
          "Bb",
          "C#",
          "F",
          "G#"
        ]
      }
    ],
    "A2": [
      {
        "notes": [
          "A",
          "C#",
          "E",
          "B"
        ]
      }
    ],
    "A4": [
      {
        "notes": [
          "A",
          "D",
          "G",
          "C"
        ]
      }
    ],
    "A5": [
      {
        "notes": [
          "A",
          "E"
        ]
      }
    ],
    "A7": [
      {
        "notes": [
          "A",
          "C#",
          "E",
          "G"
        ]
      }
    ],
    "A7M": [
      {
        "notes": [
          "A",
          "C#",
          "E",
          "G#"
        ]
      }
    ],
    "A9": [
      {
        "notes": [
          "A",
          "C#",
          "E",
          "G",
          "B"
        ]
      }
    ],
    "Ab": [
      {
        "notes": [
          "G#",
          "C",
          "Eb"
        ]
      }
    ],
    "Abm": [
      {
        "notes": [
          "G#",
          "B",
          "Eb"
        ]
      }
    ],
    "Abm7": [
      {
        "notes": [
          "G#",
          "B",
          "Eb",
          "F#"
        ]
      }
    ],
    "Adim": [
      {
        "notes": [
          "A",
          "C",
          "Eb"
        ]
      }
    ],
    "Am": [
      {
        "notes": [
          "A",
          "C",
          "E"
        ]
      }
    ],
    "Am6": [
      {
        "notes": [
          "A",
          "C",
          "E",
          "F#"
        ]
      }
    ],
    "Am7": [
      {
        "notes": [
          "A",
          "C",
          "E",
          "G"
        ]
      }
    ],
    "Am9": [
      {
        "notes": [
          "A",
          "C",
          "E",
          "G",
          "B"
        ]
      }
    ],
    "Amaj7": [
      {
        "notes": [
          "A",
          "C#",
          "E",
          "G#"
        ]
      }
    ],
    "Amaj7sus4": [
      {
        "notes": [
          "A",
          "D",
          "E",
          "G#"
        ]
      }
    ],
    "Asus2": [
      {
        "notes": [
          "A",
          "B",
          "E"
        ]
      }
    ],
    "B": [
      {
        "notes": [
          "B",
          "Eb",
          "F#"
        ]
      }
    ],
    "B+": [
      {
        "notes": [
          "B",
          "Eb",
          "G"
        ]
      }
    ],
    "B4": [
      {
        "notes": [
          "B",
          "E",
          "A",
          "D"
        ]
      }
    ],
    "B5": [
      {
        "notes": [
          "B",
          "F#"
        ]
      }
    ],
    "B7": [
      {
        "notes": [
          "B",
          "Eb",
          "F#",
          "A"
        ]
      }
    ],
    "B7M": [
      {
        "notes": [
          "B",
          "Eb",
          "F#",
          "Bb"
        ]
      }
    ],
    "B7sus4": [
      {
        "notes": [
          "B",
          "E",
          "F#",
          "A"
        ]
      }
    ],
    "B9": [
      {
        "notes": [
          "B",
          "Eb",
          "F#",
          "A",
          "C#"
        ]
      }
    ],
    "Bb": [
      {
        "notes": [
          "Bb",
          "D",
          "F"
        ]
      }
    ],
    "Bb5": [
      {
        "notes": [
          "Bb",
          "F"
        ]
      }
    ],
    "Bb6": [
      {
        "notes": [
          "Bb",
          "D",
          "F",
          "G"
        ]
      }
    ],
    "Bb7": [
      {
        "notes": [
          "Bb",
          "D",
          "F",
          "G#"
        ]
      }
    ],
    "Bb7M": [
      {
        "notes": [
          "Bb",
          "D",
          "F",
          "A"
        ]
      }
    ],
    "Bb9": [
      {
        "notes": [
          "Bb",
          "D",
          "F",
          "G#",
          "C"
        ]
      }
    ],
    "Bbadd9": [
      {
        "notes": [
          "Bb",
          "D",
          "F",
          "C"
        ]
      }
    ],
    "Bbdim": [
      {
        "notes": [
          "Bb",
          "C#",
          "E"
        ]
      }
    ],
    "Bbm": [
      {
        "notes": [
          "Bb",
          "C#",
          "F"
        ]
      }
    ],
    "Bbm#5": [
      {
        "notes": [
          "Bb",
          "C#",
          "F#"
        ]
      }
    ],
    "Bbm11": [
      {
        "notes": [
          "Bb",
          "C#",
          "F",
          "G#",
          "C",
          "Eb"
        ]
      }
    ],
    "Bbm6": [
      {
        "notes": [
          "Bb",
          "C#",
          "F",
          "G"
        ]
      }
    ],
    "Bbm7": [
      {
        "notes": [
          "Bb",
          "C#",
          "F",
          "G#"
        ]
      }
    ],
    "Bbmaj7": [
      {
        "notes": [
          "Bb",
          "D",
          "F",
          "A"
        ]
      }
    ],
    "Bdim": [
      {
        "notes": [
          "B",
          "D",
          "F"
        ]
      }
    ],
    "Bm": [
      {
        "notes": [
          "B",
          "D",
          "F#"
        ]
      }
    ],
    "Bm7": [
      {
        "notes": [
          "B",
          "D",
          "F#",
          "A"
        ]
      }
    ],
    "Bm7b5": [
      {
        "notes": [
          "B",
          "D",
          "F",
          "A"
        ]
      }
    ],
    "Bmadd9": [
      {
        "notes": [
          "B",
          "D",
          "F#",
          "C#"
        ]
      }
    ],
    "Bmaj7": [
      {
        "notes": [
          "B",
          "Eb",
          "F#",
          "Bb"
        ]
      }
    ],
    "Bsus2": [
      {
        "notes": [
          "B",
          "C#",
          "F#"
        ]
      }
    ],
    "C": [
      {
        "notes": [
          "C",
          "E",
          "G"
        ]
      }
    ],
    "C#": [
      {
        "notes": [
          "C#",
          "F",
          "G#"
        ]
      }
    ],
    "C#4": [
      {
        "notes": [
          "C#",
          "F#",
          "B",
          "E"
        ]
      }
    ],
    "C#5": [
      {
        "notes": [
          "C#",
          "G#"
        ]
      }
    ],
    "C#7": [
      {
        "notes": [
          "C#",
          "F",
          "G#",
          "B"
        ]
      }
    ],
    "C#9": [
      {
        "notes": [
          "C#",
          "F",
          "G#",
          "B",
          "Eb"
        ]
      }
    ],
    "C#dim": [
      {
        "notes": [
          "C#",
          "E",
          "G"
        ]
      }
    ],
    "C#m": [
      {
        "notes": [
          "C#",
          "E",
          "G#"
        ]
      }
    ],
    "C#m7": [
      {
        "notes": [
          "C#",
          "E",
          "G#",
          "B"
        ]
      }
    ],
    "C#m7M": [
      {
        "notes": [
          "C#",
          "E",
          "G#",
          "C"
        ]
      }
    ],
    "C#m9": [
      {
        "notes": [
          "C#",
          "E",
          "G#",
          "B",
          "Eb"
        ]
      }
    ],
    "C#maj7": [
      {
        "notes": [
          "C#",
          "F",
          "G#",
          "C"
        ]
      }
    ],
    "C69": [
      {
        "notes": [
          "C",
          "E",
          "G",
          "A",
          "D"
        ]
      }
    ],
    "C7": [
      {
        "notes": [
          "C",
          "E",
          "G",
          "Bb"
        ]
      }
    ],
    "C7M": [
      {
        "notes": [
          "C",
          "E",
          "G",
          "B"
        ]
      }
    ],
    "C9": [
      {
        "notes": [
          "C",
          "E",
          "G",
          "Bb",
          "D"
        ]
      }
    ],
    "Cadd9": [
      {
        "notes": [
          "C",
          "E",
          "G",
          "D"
        ]
      }
    ],
    "Caug": [
      {
        "notes": [
          "C",
          "E",
          "G#"
        ]
      }
    ],
    "Cdim": [
      {
        "notes": [
          "C",
          "Eb",
          "F#"
        ]
      }
    ],
    "Cm": [
      {
        "notes": [
          "C",
          "Eb",
          "G"
        ]
      }
    ],
    "Cm6": [
      {
        "notes": [
          "C",
          "Eb",
          "G",
          "A"
        ]
      }
    ],
    "Cm7": [
      {
        "notes": [
          "C",
          "Eb",
          "G",
          "Bb"
        ]
      }
    ],
    "Cmaj7": [
      {
        "notes": [
          "C",
          "E",
          "G",
          "B"
        ]
      }
    ],
    "D": [
      {
        "notes": [
          "D",
          "F#",
          "A"
        ]
      }
    ],
    "D#": [
      {
        "notes": [
          "Eb",
          "G",
          "Bb"
        ]
      }
    ],
    "D#7": [
      {
        "notes": [
          "Eb",
          "G",
          "Bb",
          "C#"
        ]
      }
    ],
    "D#dim": [
      {
        "notes": [
          "Eb",
          "F#",
          "A"
        ]
      }
    ],
    "D#dim7": [
      {
        "notes": [
          "Eb",
          "F#",
          "A",
          "C"
        ]
      }
    ],
    "D#m": [
      {
        "notes": [
          "Eb",
          "F#",
          "Bb"
        ]
      }
    ],
    "D#m7": [
      {
        "notes": [
          "Eb",
          "F#",
          "Bb",
          "C#"
        ]
      }
    ],
    "D#m7M": [
      {
        "notes": [
          "Eb",
          "F#",
          "Bb",
          "D"
        ]
      }
    ],
    "D#m7b5": [
      {
        "notes": [
          "Eb",
          "F#",
          "A",
          "C#"
        ]
      }
    ],
    "D#maj7": [
      {
        "notes": [
          "Eb",
          "G",
          "Bb",
          "D"
        ]
      }
    ],
    "D-": [
      {
        "notes": [
          "D",
          "F",
          "A"
        ]
      }
    ],
    "D4": [
      {
        "notes": [
          "D",
          "G",
          "C",
          "F"
        ]
      }
    ],
    "D5": [
      {
        "notes": [
          "D",
          "A"
        ]
      }
    ],
    "D7": [
      {
        "notes": [
          "D",
          "F#",
          "A",
          "C"
        ]
      }
    ],
    "D7#9": [
      {
        "notes": [
          "D",
          "F#",
          "A",
          "C",
          "F"
        ]
      }
    ],
    "D7M": [
      {
        "notes": [
          "D",
          "F#",
          "A",
          "C#"
        ]
      }
    ],
    "D9": [
      {
        "notes": [
          "D",
          "F#",
          "A",
          "C",
          "E"
        ]
      }
    ],
    "Db": [
      {
        "notes": [
          "C#",
          "F",
          "G#"
        ]
      }
    ],
    "Db7": [
      {
        "notes": [
          "C#",
          "F",
          "G#",
          "B"
        ]
      }
    ],
    "Dbm": [
      {
        "notes": [
          "C#",
          "E",
          "G#"
        ]
      }
    ],
    "Dbmaj7": [
      {
        "notes": [
          "C#",
          "F",
          "G#",
          "C"
        ]
      }
    ],
    "Ddim": [
      {
        "notes": [
          "D",
          "F",
          "G#"
        ]
      }
    ],
    "Dm": [
      {
        "notes": [
          "D",
          "F",
          "A"
        ]
      }
    ],
    "Dm6": [
      {
        "notes": [
          "D",
          "F",
          "A",
          "B"
        ]
      }
    ],
    "Dm7": [
      {
        "notes": [
          "D",
          "F",
          "A",
          "C"
        ]
      }
    ],
    "Dmaj7": [
      {
        "notes": [
          "D",
          "F#",
          "A",
          "C#"
        ]
      }
    ],
    "Dsus2": [
      {
        "notes": [
          "D",
          "E",
          "A"
        ]
      }
    ],
    "Dsus4": [
      {
        "notes": [
          "D",
          "G",
          "A"
        ]
      }
    ],
    "E": [
      {
        "notes": [
          "E",
          "G#",
          "B"
        ]
      }
    ],
    "E4": [
      {
        "notes": [
          "E",
          "A",
          "D",
          "G"
        ]
      }
    ],
    "E5": [
      {
        "notes": [
          "E",
          "B"
        ]
      }
    ],
    "E6": [
      {
        "notes": [
          "E",
          "G#",
          "B",
          "C#"
        ]
      }
    ],
    "E7": [
      {
        "notes": [
          "E",
          "G#",
          "B",
          "D"
        ]
      }
    ],
    "E7M": [
      {
        "notes": [
          "E",
          "G#",
          "B",
          "Eb"
        ]
      }
    ],
    "E7b13": [
      {
        "notes": [
          "E",
          "G#",
          "B",
          "C",
          "D"
        ]
      }
    ],
    "E7sus4": [
      {
        "notes": [
          "E",
          "A",
          "B",
          "D"
        ]
      }
    ],
    "E9": [
      {
        "notes": [
          "E",
          "G#",
          "B",
          "D",
          "F#"
        ]
      }
    ],
    "Eaug": [
      {
        "notes": [
          "E",
          "G#",
          "C"
        ]
      }
    ],
    "Eb": [
      {
        "notes": [
          "Eb",
          "G",
          "Bb"
        ]
      }
    ],
    "Eb7": [
      {
        "notes": [
          "Eb",
          "G",
          "Bb",
          "C#"
        ]
      }
    ],
    "Eb7M": [
      {
        "notes": [
          "Eb",
          "G",
          "Bb",
          "D"
        ]
      }
    ],
    "Ebdim": [
      {
        "notes": [
          "Eb",
          "F#",
          "A"
        ]
      }
    ],
    "Ebdim7": [
      {
        "notes": [
          "Eb",
          "F#",
          "A",
          "C"
        ]
      }
    ],
    "Ebm": [
      {
        "notes": [
          "Eb",
          "F#",
          "Bb"
        ]
      }
    ],
    "Ebmaj7": [
      {
        "notes": [
          "Eb",
          "G",
          "Bb",
          "D"
        ]
      }
    ],
    "Edim": [
      {
        "notes": [
          "E",
          "G",
          "Bb"
        ]
      }
    ],
    "Em": [
      {
        "notes": [
          "E",
          "G",
          "B"
        ]
      }
    ],
    "Em7": [
      {
        "notes": [
          "E",
          "G",
          "B",
          "D"
        ]
      }
    ],
    "Em7b5": [
      {
        "notes": [
          "E",
          "G",
          "Bb",
          "D"
        ]
      }
    ],
    "Em9": [
      {
        "notes": [
          "E",
          "G",
          "B",
          "D",
          "F#"
        ]
      }
    ],
    "Emaj7": [
      {
        "notes": [
          "E",
          "G#",
          "B",
          "Eb"
        ]
      }
    ],
    "Esus4": [
      {
        "notes": [
          "E",
          "A",
          "B"
        ]
      }
    ],
    "F": [
      {
        "notes": [
          "F",
          "A",
          "C"
        ]
      }
    ],
    "F#": [
      {
        "notes": [
          "F#",
          "Bb",
          "C#"
        ]
      }
    ],
    "F#5": [
      {
        "notes": [
          "F#",
          "C#"
        ]
      }
    ],
    "F#7": [
      {
        "notes": [
          "F#",
          "Bb",
          "C#",
          "E"
        ]
      }
    ],
    "F#dim": [
      {
        "notes": [
          "F#",
          "A",
          "C"
        ]
      }
    ],
    "F#dim7": [
      {
        "notes": [
          "F#",
          "A",
          "C",
          "Eb"
        ]
      }
    ],
    "F#m": [
      {
        "notes": [
          "F#",
          "A",
          "C#"
        ]
      }
    ],
    "F#m11": [
      {
        "notes": [
          "F#",
          "A",
          "C#",
          "E",
          "G#",
          "B"
        ]
      }
    ],
    "F#m7": [
      {
        "notes": [
          "F#",
          "A",
          "C#",
          "E"
        ]
      }
    ],
    "F#m7M": [
      {
        "notes": [
          "F#",
          "A",
          "C#",
          "F"
        ]
      }
    ],
    "F#m7b5": [
      {
        "notes": [
          "F#",
          "A",
          "C",
          "E"
        ]
      }
    ],
    "F#maj7": [
      {
        "notes": [
          "F#",
          "Bb",
          "C#",
          "F"
        ]
      }
    ],
    "F7": [
      {
        "notes": [
          "F",
          "A",
          "C",
          "Eb"
        ]
      }
    ],
    "F7M": [
      {
        "notes": [
          "F",
          "A",
          "C",
          "E"
        ]
      }
    ],
    "Fdim": [
      {
        "notes": [
          "F",
          "G#",
          "B"
        ]
      }
    ],
    "Fdim7": [
      {
        "notes": [
          "F",
          "G#",
          "B",
          "D"
        ]
      }
    ],
    "Fm": [
      {
        "notes": [
          "F",
          "G#",
          "C"
        ]
      }
    ],
    "Fm6": [
      {
        "notes": [
          "F",
          "G#",
          "C",
          "D"
        ]
      }
    ],
    "Fmaj7": [
      {
        "notes": [
          "F",
          "A",
          "C",
          "E"
        ]
      }
    ],
    "G": [
      {
        "notes": [
          "G",
          "B",
          "D"
        ]
      }
    ],
    "G#": [
      {
        "notes": [
          "G#",
          "C",
          "Eb"
        ]
      }
    ],
    "G#4": [
      {
        "notes": [
          "G#",
          "C#",
          "F#",
          "B"
        ]
      }
    ],
    "G#6": [
      {
        "notes": [
          "G#",
          "C",
          "Eb",
          "F"
        ]
      }
    ],
    "G#7": [
      {
        "notes": [
          "G#",
          "C",
          "Eb",
          "F#"
        ]
      }
    ],
    "G#dim": [
      {
        "notes": [
          "G#",
          "B",
          "D"
        ]
      }
    ],
    "G#dim7": [
      {
        "notes": [
          "G#",
          "B",
          "D",
          "F"
        ]
      }
    ],
    "G#m": [
      {
        "notes": [
          "G#",
          "B",
          "Eb"
        ]
      }
    ],
    "G#m11": [
      {
        "notes": [
          "G#",
          "B",
          "Eb",
          "F#",
          "Bb",
          "C#"
        ]
      }
    ],
    "G#m7": [
      {
        "notes": [
          "G#",
          "B",
          "Eb",
          "F#"
        ]
      }
    ],
    "G5": [
      {
        "notes": [
          "G",
          "D"
        ]
      }
    ],
    "G6": [
      {
        "notes": [
          "G",
          "B",
          "D",
          "E"
        ]
      }
    ],
    "G7": [
      {
        "notes": [
          "G",
          "B",
          "D",
          "F"
        ]
      }
    ],
    "G7M": [
      {
        "notes": [
          "G",
          "B",
          "D",
          "F#"
        ]
      }
    ],
    "G9": [
      {
        "notes": [
          "G",
          "B",
          "D",
          "F",
          "A"
        ]
      }
    ],
    "Gaug": [
      {
        "notes": [
          "G",
          "B",
          "Eb"
        ]
      }
    ],
    "Gb": [
      {
        "notes": [
          "F#",
          "Bb",
          "C#"
        ]
      }
    ],
    "Gdim": [
      {
        "notes": [
          "G",
          "Bb",
          "C#"
        ]
      }
    ],
    "Gdim7": [
      {
        "notes": [
          "G",
          "Bb",
          "C#",
          "E"
        ]
      }
    ],
    "Gm": [
      {
        "notes": [
          "G",
          "Bb",
          "D"
        ]
      }
    ],
    "Gm6": [
      {
        "notes": [
          "G",
          "Bb",
          "D",
          "E"
        ]
      }
    ],
    "Gm7": [
      {
        "notes": [
          "G",
          "Bb",
          "D",
          "F"
        ]
      }
    ],
    "Gm7M": [
      {
        "notes": [
          "G",
          "Bb",
          "D",
          "F#"
        ]
      }
    ],
    "Gmaj7": [
      {
        "notes": [
          "G",
          "B",
          "D",
          "F#"
        ]
      }
    ],
    "Gsus4": [
      {
        "notes": [
          "G",
          "C",
          "D"
        ]
      }
    ]
  }
}
